linksaas_local_api/__init__.py
linksaas_local_api/api_client.py
linksaas_local_api/configuration.py
linksaas_local_api/exceptions.py
linksaas_local_api/model_utils.py
linksaas_local_api/rest.py
linksaas_local_api/api/__init__.py
linksaas_local_api/api/global_api.py
linksaas_local_api/api/project_bug_api.py
linksaas_local_api/api/project_channel_api.py
linksaas_local_api/api/project_content_block_api.py
linksaas_local_api/api/project_create_api.py
linksaas_local_api/api/project_doc_api.py
linksaas_local_api/api/project_event_api.py
linksaas_local_api/api/project_member_api.py
linksaas_local_api/api/project_task_api.py
linksaas_local_api/apis/__init__.py
linksaas_local_api/model/__init__.py
linksaas_local_api/model/block_coll_info.py
linksaas_local_api/model/block_content_info.py
linksaas_local_api/model/block_info.py
linksaas_local_api/model/bug_info.py
linksaas_local_api/model/channel_info.py
linksaas_local_api/model/doc_info.py
linksaas_local_api/model/doc_space_info.py
linksaas_local_api/model/err_info.py
linksaas_local_api/model/event_info.py
linksaas_local_api/model/issue_info.py
linksaas_local_api/model/msg_info.py
linksaas_local_api/model/project_project_id_block_coll_block_coll_id_get200_response.py
linksaas_local_api/model/project_project_id_block_coll_get200_response.py
linksaas_local_api/model/project_project_id_bug_all_get200_response.py
linksaas_local_api/model/project_project_id_doc_space_doc_space_id_get200_response.py
linksaas_local_api/model/project_project_id_event_get200_response.py
linksaas_local_api/model/project_project_id_task_all_get200_response.py
linksaas_local_api/model/project_project_id_task_record_task_id_depend_get200_response.py
linksaas_local_api/model/simple_member_info.py
linksaas_local_api/model/sub_task_info.py
linksaas_local_api/model/task_info.py
linksaas_local_api/models/__init__.py
linksaas_local_api-0.0.4.dist-info/METADATA
linksaas_local_api-0.0.4.dist-info/WHEEL
linksaas_local_api-0.0.4.dist-info/top_level.txt
linksaas_local_api-0.0.4.dist-info/RECORD
